[
  {
    "id": "7af92140-a792-4600-9573-dbdf639c6f9d",
    "title": "1222",
    "description": "string",
    "createdAt": 123123123,
    "updatedAt": "timestamp",
    "deadlineDate": 123123123,
    "status": "in progress",
    "priority": 1,
    "color": "red",
    "userId": 123123123
  },
  {
    "id": "89ef31ab-a580-41b1-8e17-b84169d8e6ab",
    "title": "dima test update",
    "description": "string",
    "createdAt": 123123123,
    "updatedAt": "timestamp",
    "deadlineDate": 123123123,
    "status": "in progress",
    "priority": 1,
    "color": "red",
    "userId": 123123123
  },
  {
    "id": "3cf70c1e-9a2c-433d-bb24-703b98f445d8",
    "title": "test test",
    "description": "string",
    "createdAt": 123123123,
    "updatedAt": "timestamp",
    "deadlineDate": 123123123,
    "status": "in progress",
    "priority": 1,
    "color": "red",
    "userId": 123123123
  },
  {
    "id": "91db72a3-ed4f-46fc-a8cc-5ca75ae89670",
    "title": "dimasos",
    "description": "string",
    "createdAt": 123123123,
    "updatedAt": "timestamp",
    "deadlineDate": 123123123,
    "status": "in progress",
    "priority": 1,
    "color": "red",
    "userId": 123123123
  },
  {
    "id": "43020845-f8e9-4306-b19e-8a3a425d0353",
    "title": "fdgdfdfgdfg",
    "description": "string",
    "createdAt": 123123123,
    "updatedAt": "timestamp",
    "deadlineDate": 123123123,
    "status": "in progress",
    "priority": 1,
    "color": "red",
    "userId": 123123123
  },
  {
    "id": "1465345a-f019-45c2-b44a-dd70b821e307",
    "title": "dimasos",
    "description": "string",
    "createdAt": 123123123,
    "updatedAt": "timestamp",
    "deadlineDate": 123123123,
    "status": "in progress",
    "priority": 1,
    "color": "red",
    "userId": 123123123
  },
  {
    "id": "9b7dfb8b-5533-4a6c-a056-a900087e08bb",
    "title": "dimasos",
    "description": "string",
    "createdAt": 123123123,
    "updatedAt": "timestamp",
    "deadlineDate": 123123123,
    "status": "in progress",
    "priority": 1,
    "color": "red",
    "userId": 123123123
  },
  {
    "id": "d566d109-f7bb-467d-89ca-d71abec94b3f",
    "title": "dimasoss",
    "description": "string",
    "createdAt": 123123123,
    "updatedAt": "timestamp",
    "deadlineDate": 123123123,
    "status": "in progress",
    "priority": 1,
    "color": "red",
    "userId": 123123123
  },
  {
    "id": "a986d809-d208-46f7-a38c-b8087a9110a6",
    "title": "dimasoss",
    "description": "string",
    "createdAt": 123123123,
    "updatedAt": "timestamp",
    "deadlineDate": 123123123,
    "status": "in progress",
    "priority": 1,
    "color": "red",
    "userId": 123123123
  },
  {
    "id": "fdea1730-df5b-4221-a934-31559b7342c8",
    "title": "dimasoss",
    "description": "string",
    "createdAt": 123123123,
    "updatedAt": "timestamp",
    "deadlineDate": 123123123,
    "status": "in progress",
    "priority": 1,
    "color": "red",
    "userId": 123123123
  }
]